[{"text":"Lead","id":"e519642b-2269-45a4-97ee-3ef8e9832485","url":"/leads","activeUrls":["/leads","/leads/edit"],"items":[]},{"text":"Opportunity","id":"a6a519ff-9594-4378-9562-dcfef73ddf88","url":"/opportunity","activeUrls":["/opportunity","/opportunity/edit"],"items":[]},{"text":"Customer","id":"a76ab1c2-a12c-4a1c-979e-efe9b264cb62","url":"/customer","activeUrls":["/customer","/customer/edit"],"items":[]},{"text":"Quotation","id":"753eff52-ef8a-494d-93ea-97cf54e3e8f9","url":"/quotation","activeUrls":["/quotation","/quotation/edit"],"items":[]},{"text":"Invoice","id":"c5a4977a-adbf-4ef7-a208-ddadacccd954","url":"/invoice","activeUrls":["/invoice","/invoice/edit"],"items":[]},{"text":"Tax","id":"9d5f0919-f040-49be-9d49-f25e22ce955d","url":"/tax","activeUrls":["/tax","/tax/edit"],"items":[]},{"text":"Products","items":[{"id":"83ca8283-14cb-428d-923a-e0f83d2a20d6","text":"Product","url":"/product","activeUrls":["/product","/product/edit"]},{"id":"bcc0b1f0-a9a2-4d4f-8920-401247bed0e7","text":"Product group","url":"/productgroup","activeUrls":["/productgroup","/productgroup/edit"]}]},{"text":"Setting","items":[{"id":"d085e302-5753-40cf-a34e-24dff4e2b495","text":"Lead source","url":"/setting/leadsource","activeUrls":["/setting/leadsource","/setting/leadsource/edit"]},{"id":"04b9b210-9ab4-40f0-a93a-a00214694c72","text":"Activity status","url":"/setting/activitystatus","activeUrls":["/setting/activitystatus","/setting/activitystatus/edit"]},{"id":"022526ae-77b8-4e1e-ba4a-93e8b62453b9","text":"Activity type","url":"/setting/activitytype","activeUrls":["/setting/activitytype","/setting/activitytype/edit"]}]},{"text":"Oragnization","items":[{"id":"f60f873c-4c45-4c34-b93f-ceec6aa43e34","text":"Locations","url":"/organization/locations","activeUrls":["/organization/locations","/organization/location/edit","/organization/departments","/organization/department/edit","/organization/teams","/organization/team/edit"]}]},{"text":"User","items":[{"id":"ae7a3406-47c6-4638-9413-6fed04b2f730","text":"Users","url":"/users","activeUrls":["/users","/user/edit","/user/teams","/user/roles","/user/password"]},{"id":"2e3b4c47-23cb-40b6-9cd8-dc3fd28c1a0f","text":"Role Base","url":"/user/rolebases","activeUrls":["/user/rolebases","/user/rolebase/edit","/user/rolebase/access","/user/rolebase/access/edit","/user/rolebase/organization"]}]}]